sirifi/__init__.py
sirifi/crypto_back_test.py
sirifi/crypto_dashboard.py
sirifi/crypto_feature_engineering.py
sirifi/crypto_sentiment.py
sirifi/crypto_streamer.py
sirifi/crypto_value_investment.py
sirifi/value_investment.py
sirifi-2.0.0.dist-info/METADATA
sirifi-2.0.0.dist-info/WHEEL
sirifi-2.0.0.dist-info/top_level.txt
sirifi-2.0.0.dist-info/RECORD
