Metadata-Version: 2.1
Name: sirifi
Version: 2.0.0
Summary: SiriFi: Smart Insights & Research for Investments in Financial Instruments
Home-page: https://github.com/CodeEagle22/SiriFi
Author: Sagar Narwade, Rudra Desai
Classifier: Programming Language :: Python :: 3
Classifier: Operating System :: OS Independent
Classifier: License :: OSI Approved :: MIT License
Requires-Python: ==3.11
Requires-Dist: aiohappyeyeballs ==2.6.1
Requires-Dist: aiohttp ==3.12.13
Requires-Dist: aiosignal ==1.4.0
Requires-Dist: alpha-vantage ==3.0.0
Requires-Dist: anyio ==4.9.0
Requires-Dist: attrs ==25.3.0
Requires-Dist: backports.tarfile ==1.2.0
Requires-Dist: beautifulsoup4 ==4.13.4
Requires-Dist: binance ==0.3.55
Requires-Dist: build ==1.3.0
Requires-Dist: certifi ==2025.6.15
Requires-Dist: cffi ==1.17.1
Requires-Dist: charset-normalizer ==3.4.2
Requires-Dist: contourpy ==1.3.2
Requires-Dist: cryptography ==45.0.5
Requires-Dist: curl-cffi ==0.11.4
Requires-Dist: cycler ==0.12.1
Requires-Dist: dateparser ==1.2.2
Requires-Dist: docutils ==0.22
Requires-Dist: dotenv ==0.9.9
Requires-Dist: fastjsonschema ==2.21.2
Requires-Dist: fonttools ==4.58.5
Requires-Dist: frozendict ==2.4.6
Requires-Dist: frozenlist ==1.7.0
Requires-Dist: greenlet ==3.2.4
Requires-Dist: h11 ==0.16.0
Requires-Dist: httpcore ==1.0.9
Requires-Dist: httpx ==0.28.1
Requires-Dist: id ==1.5.0
Requires-Dist: jsonschema ==4.25.1
Requires-Dist: jsonschema-specifications ==2025.9.1
Requires-Dist: jaraco.classes ==3.4.0
Requires-Dist: jaraco.context ==6.0.1
Requires-Dist: jaraco.functools ==4.2.1
Requires-Dist: jedi ==0.18.2
Requires-Dist: markdown-it-py ==3.0.0
Requires-Dist: matplotlib ==3.10.3
Requires-Dist: mdurl ==0.1.2
Requires-Dist: more-itertools ==10.7.0
Requires-Dist: multidict ==6.6.3
Requires-Dist: multitasking ==0.0.11
Requires-Dist: narwhals ==2.5.0
Requires-Dist: nbformat ==5.10.4
Requires-Dist: newsapi ==0.1.1
Requires-Dist: newsapi-python ==0.2.7
Requires-Dist: nh3 ==0.3.0
Requires-Dist: numpy ==1.26.4
Requires-Dist: openpyxl ==3.1.5
Requires-Dist: pandas ==2.3.0
Requires-Dist: patsy ==1.0.1
Requires-Dist: peewee ==3.18.1
Requires-Dist: pickleshare ==0.7.5
Requires-Dist: pillow ==11.3.0
Requires-Dist: playwright ==1.54.0
Requires-Dist: plotly ==6.3.0
Requires-Dist: praw ==7.8.1
Requires-Dist: prawcore ==2.4.0
Requires-Dist: propcache ==0.3.2
Requires-Dist: protobuf ==6.31.1
Requires-Dist: pycparser ==2.22
Requires-Dist: pycryptodome ==3.23.0
Requires-Dist: pyee ==13.0.0
Requires-Dist: Pygments ==2.16.1
Requires-Dist: pyparsing ==3.2.3
Requires-Dist: pyproject-hooks ==1.2.0
Requires-Dist: PySocks ==1.7.1
Requires-Dist: python-binance ==1.0.29
Requires-Dist: python-dotenv ==1.1.1
Requires-Dist: python-telegram-bot ==22.3
Requires-Dist: pytz ==2025.2
Requires-Dist: readme-renderer ==44.0
Requires-Dist: referencing ==0.36.2
Requires-Dist: regex ==2024.11.6
Requires-Dist: requests ==2.32.4
Requires-Dist: requests-futures ==1.0.2
Requires-Dist: requests-toolbelt ==1.0.0
Requires-Dist: rfc3986 ==2.0.0
Requires-Dist: rich ==14.1.0
Requires-Dist: rpds-py ==0.27.1
Requires-Dist: schedule ==1.2.2
Requires-Dist: scipy ==1.10.1
Requires-Dist: seaborn ==0.13.2
Requires-Dist: selenium ==4.34.0
Requires-Dist: six ==1.16.0
Requires-Dist: sniffio ==1.3.1
Requires-Dist: sortedcontainers ==2.4.0
Requires-Dist: soupsieve ==2.7
Requires-Dist: statsmodels ==0.13.5
Requires-Dist: stocktrends ==0.1.5
Requires-Dist: ta ==0.11.0
Requires-Dist: tqdm ==4.67.1
Requires-Dist: trio ==0.30.0
Requires-Dist: trio-websocket ==0.12.2
Requires-Dist: twine ==6.1.0
Requires-Dist: typing-extensions ==4.14.0
Requires-Dist: tzdata ==2025.2
Requires-Dist: tzlocal ==5.3.1
Requires-Dist: update-checker ==0.18.0
Requires-Dist: urllib3 ==2.4.0
Requires-Dist: vaderSentiment ==3.3.2
Requires-Dist: websocket-client ==1.8.0
Requires-Dist: websockets ==15.0.1
Requires-Dist: wsproto ==1.2.0
Requires-Dist: yahooquery ==2.4.1
Requires-Dist: yarl ==1.20.1
Requires-Dist: yfinance ==0.2.64
